kivymd/__init__.py
kivymd/accordion.py
kivymd/backgroundcolorbehavior.py
kivymd/bottomsheet.py
kivymd/button.py
kivymd/card.py
kivymd/color_definitions.py
kivymd/date_picker.py
kivymd/dialog.py
kivymd/elevationbehavior.py
kivymd/grid.py
kivymd/icon_definitions.py
kivymd/label.py
kivymd/list.py
kivymd/material_resources.py
kivymd/menu.py
kivymd/navigationdrawer.py
kivymd/progressbar.py
kivymd/ripplebehavior.py
kivymd/selectioncontrols.py
kivymd/slider.py
kivymd/slidingpanel.py
kivymd/snackbar.py
kivymd/spinner.py
kivymd/tabs.py
kivymd/textfields.py
kivymd/theme_picker.py
kivymd/theming.py
kivymd/theming_dynamic_text.py
kivymd/time_picker.py
kivymd/toolbar.py
kivymd/version.py
kivymd/fonts/Roboto-Bold.ttf
kivymd/fonts/Roboto-Italic.ttf
kivymd/fonts/Roboto-Light.ttf
kivymd/fonts/Roboto-LightItalic.ttf
kivymd/fonts/Roboto-Medium.ttf
kivymd/fonts/Roboto-MediumItalic.ttf
kivymd/fonts/Roboto-Regular.ttf
kivymd/fonts/Roboto-Thin.ttf
kivymd/fonts/Roboto-ThinItalic.ttf
kivymd/fonts/materialdesignicons-webfont.ttf
kivymd/images/kivymd_512.png
kivymd/images/kivymd_logo.png
kivymd/images/quad_shadow-0.png
kivymd/images/quad_shadow-1.png
kivymd/images/quad_shadow-2.png
kivymd/images/quad_shadow.atlas
kivymd/images/rec_shadow-0.png
kivymd/images/rec_shadow-1.png
kivymd/images/rec_shadow.atlas
kivymd/images/rec_st_shadow-0.png
kivymd/images/rec_st_shadow-1.png
kivymd/images/rec_st_shadow-2.png
kivymd/images/rec_st_shadow.atlas
kivymd/images/round_shadow-0.png
kivymd/images/round_shadow-1.png
kivymd/images/round_shadow-2.png
kivymd/images/round_shadow.atlas
kivymd/images/transparent.png
kivymd/vendor/__init__.py
kivymd/vendor/circleLayout/__init__.py
kivymd/vendor/circularTimePicker/__init__.py
kivymd/vendor/navigationdrawer/__init__.py
kivy_garden.kivymd-2019.910.dist-info/LICENSE
kivy_garden.kivymd-2019.910.dist-info/METADATA
kivy_garden.kivymd-2019.910.dist-info/WHEEL
kivy_garden.kivymd-2019.910.dist-info/top_level.txt
kivy_garden.kivymd-2019.910.dist-info/RECORD
