Metadata-Version: 2.1
Name: kivy_garden.kivymd
Version: 2019.910
Summary: Set of widgets for Kivy inspired by Google's Material Design
Home-page: https://github.com/AndreMiras/KivyMD
Author: Andrés Rodríguez
Author-email: andres.rodriguez@lithersoft.com
License: UNKNOWN
Platform: UNKNOWN
